iptoolv4/README.MD
iptoolv4/__init__.py
iptoolv4/requirements.txt
iptoolv4/thirdparty.json
iptoolv4-0.10.dist-info/LICENSE.rst
iptoolv4-0.10.dist-info/METADATA
iptoolv4-0.10.dist-info/WHEEL
iptoolv4-0.10.dist-info/top_level.txt
iptoolv4-0.10.dist-info/RECORD
