Metadata-Version: 2.1
Name: iptoolv4
Version: 0.10
Summary: Finds ipv4 addresses in log files / stdout
Home-page: https://github.com/hansalemaos/iptoolv4
Author: Johannes Fischer
Author-email: aulasparticularesdealemaosp@gmail.com
License: MIT
Keywords: ipv4
Classifier: Development Status :: 4 - Beta
Classifier: Programming Language :: Python :: 3 :: Only
Classifier: Programming Language :: Python :: 3.10
Classifier: Topic :: Software Development :: Libraries :: Python Modules
Classifier: Topic :: Utilities
License-File: LICENSE.rst
Requires-Dist: PrettyColorPrinter
Requires-Dist: cprinter
Requires-Dist: disable-warnings
Requires-Dist: getpublicipv4
Requires-Dist: numexpr
Requires-Dist: numpy
Requires-Dist: pandas
Requires-Dist: regex
Requires-Dist: touchtouch
Requires-Dist: umacajadada
